script/__init__.py
video_konverter-0.0.1.dist-info/LICENSE
video_konverter-0.0.1.dist-info/METADATA
video_konverter-0.0.1.dist-info/WHEEL
video_konverter-0.0.1.dist-info/top_level.txt
video_konverter-0.0.1.dist-info/RECORD
