Metadata-Version: 2.1
Name: video-konverter
Version: 0.0.1
Summary: Convert video files using ffmpeg.
Home-page: https://github.com/SyntaxualSugar/VideoKonverter
Author: Trenton Fox
Author-email: tcfox54@gmail.com
License: UNKNOWN
Platform: UNKNOWN
Classifier: Programming Language :: Python :: 3
Classifier: License :: OSI Approved :: GNU General Public License v3 (GPLv3)
Classifier: Operating System :: POSIX :: Linux
Classifier: Environment :: Console
Requires-Python: >=3.6
